zinolib/__init__.py
zinolib/compat.py
zinolib/event_types.py
zinolib/ritz.py
zinolib/utils.py
zinolib/version.py
zinolib/zino_emu.py
zinolib/config/__init__.py
zinolib/config/models.py
zinolib/config/tcl.py
zinolib/config/toml.py
zinolib/config/utils.py
zinolib/config/zino1.py
zinolib/controllers/__init__.py
zinolib/controllers/base.py
zinolib/controllers/zino1.py
zinolib-1.3.4.dist-info/licenses/LICENSE
zinolib-1.3.4.dist-info/METADATA
zinolib-1.3.4.dist-info/WHEEL
zinolib-1.3.4.dist-info/top_level.txt
zinolib-1.3.4.dist-info/RECORD
