Metadata-Version: 2.4
Name: zinolib
Version: 1.3.4
Summary: Python interface to Zino
Author-email: Runar Borge <runar.borge@sikt.no>
Maintainer-email: Uninett Opensource <opensource@uninett.no>
License: 
Platform: any
Classifier: Intended Audience :: Information Technology
Classifier: Intended Audience :: System Administrators
Classifier: Programming Language :: Python :: 3 :: Only
Classifier: Programming Language :: Python :: 3.9
Classifier: Programming Language :: Python :: 3.10
Classifier: Programming Language :: Python :: 3.11
Classifier: Programming Language :: Python :: 3.12
Classifier: Topic :: System :: Monitoring
Requires-Python: >=3.9
License-File: LICENSE
Requires-Dist: pydantic>=2.0
Requires-Dist: tomli; python_version < "3.11"
Dynamic: license-file
